odapqi/api/__init__.py
odapqi/api/classes/export_api.py
odapqi/api/classes/persona_api.py
odapqi/api/classes/qi_api.py
odapqi/api/classes/qi_api_preprocessing.py
odapqi/api/classes/qi_runners.py
odapqi/api/classes/segment_api.py
odapqi/api/functions.py
odapqi/api/qi_helpers.py
odapqi/display/__init__.py
odapqi/display/components/export/export.py
odapqi/display/components/main.py
odapqi/display/components/overview/overview.py
odapqi/display/components/segment/attribute.py
odapqi/display/components/segment/attributes.py
odapqi/display/components/segment/save.py
odapqi/display/components/segment/segment.py
odapqi/display/components/segment/selector.py
odapqi/display/components/tabs/tab.py
odapqi/logger.py
odapqi/main.py
odap_qi-0.1.1.dist-info/LICENSE
odap_qi-0.1.1.dist-info/WHEEL
odap_qi-0.1.1.dist-info/METADATA
odap_qi-0.1.1.dist-info/RECORD
