Metadata-Version: 2.1
Name: odap-qi
Version: 0.1.1
Summary: ODAP Quick Insights
Home-page: https://github.com/DataSentics/odap-qi
License: Proprietary
Author: Jan Petrik
Author-email: jan.petrik@datasentics.com
Requires-Python: >=3.8,<4.0
Classifier: License :: Other/Proprietary License
Classifier: Programming Language :: Python :: 3
Classifier: Programming Language :: Python :: 3.8
Classifier: Programming Language :: Python :: 3.9
Classifier: Programming Language :: Python :: 3.10
Classifier: Programming Language :: Python :: 3.11
Project-URL: Repository, https://github.com/DataSentics/odap-qi
